pyexecmd-0.1.9.dist-info/licenses/LICENSE
pymd/__init__.py
pymd/api_routes.py
pymd/cli.py
pymd/code_executor.py
pymd/file_watcher.py
pymd/html_generator.py
pymd/image_handler.py
pymd/logger.py
pymd/markdown_processor.py
pymd/pdf_exporter.py
pymd/pymd_elements.py
pymd/renderer.py
pymd/server.py
pymd/static_routes.py
pymd/templates.py
pymd/video_handler.py
pymd/static/css/pymd.css
pymd/static/js/dark-mode.js
pyexecmd-0.1.9.dist-info/METADATA
pyexecmd-0.1.9.dist-info/WHEEL
pyexecmd-0.1.9.dist-info/entry_points.txt
pyexecmd-0.1.9.dist-info/top_level.txt
pyexecmd-0.1.9.dist-info/RECORD
