Metadata-Version: 2.4
Name: pyexecmd
Version: 0.1.9
Summary: Python-Powered Markdown with executable code and dynamic content
Author: PyExecMD Team
Maintainer: PyExecMD Team
License: MIT
Project-URL: Homepage, https://github.com/treeleaves30760/PyMD
Project-URL: Bug Reports, https://github.com/treeleaves30760/PyMD/issues
Project-URL: Source, https://github.com/treeleaves30760/PyMD
Keywords: markdown,python,documentation,jupyter,notebook
Classifier: Development Status :: 3 - Alpha
Classifier: Intended Audience :: Developers
Classifier: Intended Audience :: Science/Research
Classifier: Topic :: Documentation
Classifier: Topic :: Text Processing :: Markup
Classifier: License :: OSI Approved :: MIT License
Classifier: Programming Language :: Python :: 3
Classifier: Programming Language :: Python :: 3.8
Classifier: Programming Language :: Python :: 3.9
Classifier: Programming Language :: Python :: 3.10
Classifier: Programming Language :: Python :: 3.11
Classifier: Programming Language :: Python :: 3.12
Requires-Python: >=3.8
License-File: LICENSE
Requires-Dist: Flask>=3.0.0
Requires-Dist: Flask-SocketIO>=5.3.0
Requires-Dist: matplotlib>=3.8.0
Requires-Dist: pandas>=2.1.0
Requires-Dist: numpy>=2.0.0
Requires-Dist: watchdog>=6.0.0
Requires-Dist: python-socketio>=5.8.0
Requires-Dist: Werkzeug>=3.0.0
Provides-Extra: dev
Requires-Dist: pytest>=6.0; extra == "dev"
Requires-Dist: pytest-cov; extra == "dev"
Requires-Dist: black; extra == "dev"
Requires-Dist: flake8; extra == "dev"
Requires-Dist: mypy; extra == "dev"
Requires-Dist: isort; extra == "dev"
Requires-Dist: pre-commit; extra == "dev"
Dynamic: license-file
